robustvsnormalzoo/__init__.py
robustvsnormalzoo/model_mappings.csv
robustvsnormalzoo/utils.py
tests/__init__.py
tests/test_model_zoo.py
robustvsnormalzoo-1.0.4.dist-info/METADATA
robustvsnormalzoo-1.0.4.dist-info/WHEEL
robustvsnormalzoo-1.0.4.dist-info/top_level.txt
robustvsnormalzoo-1.0.4.dist-info/RECORD
